ZeroSeg/__init__.py
ZeroSeg/buttons.py
ZeroSeg/led.py
ZeroSeg_Improved-0.3.dist-info/LICENSE
ZeroSeg_Improved-0.3.dist-info/METADATA
ZeroSeg_Improved-0.3.dist-info/WHEEL
ZeroSeg_Improved-0.3.dist-info/top_level.txt
ZeroSeg_Improved-0.3.dist-info/RECORD
