Metadata-Version: 2.1
Name: ZeroSeg-Improved
Version: 0.3
Summary: Improved code library for the ZeroSeg display board for the Raspberry Pi.
Home-page: https://github.com/samedamci/ZeroSeg
Author: Richard Saville, samedamci
Author-email: samedamci@disroot.org
License: MIT
Project-URL: Issue tracker, https://github.com/samedamci/ZeroSeg/issues
Project-URL: Documentation, https://github.com/samedamci/ZeroSeg/wiki
Keywords: raspberry pi rpi led max7219 matrix seven segment zeroseg
Platform: UNKNOWN
Classifier: Intended Audience :: Developers
Classifier: Programming Language :: Python :: 3
Classifier: Programming Language :: Python :: 3.5
Classifier: Programming Language :: Python :: 3.6
Classifier: Programming Language :: Python :: 3.7
Classifier: Programming Language :: Python :: 3.8
Classifier: Programming Language :: Python :: 3 :: Only
Classifier: Programming Language :: Python :: Implementation :: CPython
Classifier: Programming Language :: Python :: Implementation :: PyPy
Classifier: License :: OSI Approved :: MIT License
Classifier: Operating System :: POSIX :: Linux
Requires-Python: >=3.6
Requires-Dist: RPi.GPIO
Requires-Dist: spidev
